scdf_processor/.DS_Store
scdf_processor/__init__.py
scdf_processor/http_status_server.py
scdf_processor/processor.py
scdf_processor/task_args.py
scdf_processor-0.1.1.dist-info/WHEEL
scdf_processor-0.1.1.dist-info/METADATA
scdf_processor-0.1.1.dist-info/RECORD
