Metadata-Version: 2.1
Name: scdf-processor
Version: 0.1.1
Summary: 
Author: Your Name
Author-email: you@example.com
Requires-Python: >=3.6,<4.0
Classifier: Programming Language :: Python :: 3
Classifier: Programming Language :: Python :: 3.6
Classifier: Programming Language :: Python :: 3.7
Requires-Dist: kafka-python (>=1.4,<2.0)
